spawndb/__init__.py
spawndb/aio.py
spawndb/spawndb.py
spawndb-0.1.18.dist-info/WHEEL
spawndb-0.1.18.dist-info/METADATA
spawndb-0.1.18.dist-info/RECORD
