Metadata-Version: 2.1
Name: spawndb
Version: 0.1.18
Summary: 
Home-page: https://github.com/ppmdo/spawndb
Author: Pablo Prieto
Author-email: pabloprieto@live.com
Requires-Python: >=3.9,<4.0
Classifier: Programming Language :: Python :: 3
Classifier: Programming Language :: Python :: 3.9
Classifier: Programming Language :: Python :: 3.10
Classifier: Programming Language :: Python :: 3.11
Requires-Dist: SQLAlchemy[asyncio] (>1.4.0,<3.0.0)
Project-URL: Repository, https://github.com/ppmdo/spawndb
